plac.py
plac_core.py
plac_ext.py
plac_tk.py
plac-1.4.1.data/scripts/plac_runner.py
plac-1.4.1.dist-info/LICENSE.txt
plac-1.4.1.dist-info/METADATA
plac-1.4.1.dist-info/WHEEL
plac-1.4.1.dist-info/top_level.txt
plac-1.4.1.dist-info/RECORD
