Metadata-Version: 2.1
Name: plac
Version: 1.4.1
Summary: The smartest command line arguments parser in the world
Home-page: https://github.com/ialbert/plac
Author: Michele Simionato
Author-email: michele.simionato@gmail.com
License: BSD License
Keywords: command line arguments parser
Platform: All
Classifier: Development Status :: 5 - Production/Stable
Classifier: Intended Audience :: Developers
Classifier: License :: OSI Approved :: BSD License
Classifier: Natural Language :: English
Classifier: Operating System :: OS Independent
Classifier: Programming Language :: Python
Classifier: Programming Language :: Python :: 3
Classifier: Topic :: Software Development :: Libraries
Classifier: Topic :: Utilities
License-File: LICENSE.txt
